AUTHORS
LICENSE
MANIFEST.in
README.rst
setup.py
pyjade_coffin/__init__.py
pyjade_coffin/app_settings.py
pyjade_coffin/common.py
pyjade_coffin.egg-info/PKG-INFO
pyjade_coffin.egg-info/SOURCES.txt
pyjade_coffin.egg-info/dependency_links.txt
pyjade_coffin.egg-info/requires.txt
pyjade_coffin.egg-info/top_level.txt
pyjade_coffin/shortcuts/__init__.py
pyjade_coffin/template/__init__.py
pyjade_coffin/template/loader.py
pyjade_coffin/templatetags/__init__.py
pyjade_coffin/templatetags/pyjade_coffin_tags.py