Metadata-Version: 1.1
Name: pyjade-coffin
Version: 0.1.0.dev
Summary: Jade and Jinja2 template support for Django using PyJade's Jinja2 extension w/ coffin
Home-page: http://github.com/AbleCoder/pyjade_coffin
Author: Brandon Orther
Author-email: an.able.coder@gmail.com
License: LICENSE
Platform: UNKNOWN
Classifier: Framework :: Django
Classifier: Intended Audience :: Developers
Classifier: Intended Audience :: System Administrators
Classifier: Operating System :: OS Independent
Classifier: Topic :: Software Development
